majocol/__init__.py
majocol/color.py
majocol/convert.py
majocol/utils.py
majocol-0.1.6.dist-info/LICENSE
majocol-0.1.6.dist-info/WHEEL
majocol-0.1.6.dist-info/METADATA
majocol-0.1.6.dist-info/RECORD
